README.rst
setup.py
pysubtracking.egg-info/PKG-INFO
pysubtracking.egg-info/SOURCES.txt
pysubtracking.egg-info/dependency_links.txt
pysubtracking.egg-info/requires.txt
pysubtracking.egg-info/top_level.txt
subtracking/__init__.py
subtracking/datagenerator.py
subtracking/error_tools.py
subtracking/grouse.py
subtracking/petrels.py
subtracking/tracker.py