Metadata-Version: 1.1
Name: pysubtracking
Version: 0.0.1
Summary: Python implementation of subspace estimation and tracking methods.
Home-page: https://github.com/hasselg/pysubtracking
Author: Gregory (Greg) Hasseler
Author-email: ghasseler@gmail.com
License: APLv2
Keywords: subspace estimation tracking
Platform: UNKNOWN
Classifier: Development Status :: 3 - Alpha
Classifier: Intended Audience :: Science/Research
Classifier: Topic :: Scientific/Engineering
Classifier: Topic :: Scientific/Engineering :: Mathematics
Classifier: License :: OSI Approved :: Apache Software License
Classifier: Programming Language :: Python :: 3 :: Only
